captchascraper/__init__.py
captchascraper-0.0.9.dist-info/METADATA
captchascraper-0.0.9.dist-info/WHEEL
captchascraper-0.0.9.dist-info/top_level.txt
captchascraper-0.0.9.dist-info/RECORD
