Metadata-Version: 2.1
Name: captchascraper
Version: 0.0.9
Summary: Captcha Bypass API
Home-page: https://github.com/zearakun/captchascraper
Author: zearadiscord
License: UNKNOWN
Platform: UNKNOWN
Classifier: Programming Language :: Python :: 3
Classifier: License :: OSI Approved :: MIT License
Classifier: Operating System :: OS Independent
